HACKING.txt
MANIFEST.in
NEWS.txt
README.rst
setup.py
src/twerp/__init__.py
src/twerp/cli.py
src/twerp/twilio_support.py
src/twerp.egg-info/PKG-INFO
src/twerp.egg-info/SOURCES.txt
src/twerp.egg-info/dependency_links.txt
src/twerp.egg-info/entry_points.txt
src/twerp.egg-info/not-zip-safe
src/twerp.egg-info/requires.txt
src/twerp.egg-info/top_level.txt