Metadata-Version: 1.0
Name: twerp
Version: 0.0.5
Summary: Twilio command-line application for sending SMS text messages and making voice calls.
Home-page: http://github.com/cakebread/twerp
Author: Rob Cakebread
Author-email: cakebread@gmail.com
License: BSD
Keywords: twilio sms telephony
Platform: UNKNOWN
Classifier: Development Status :: 2 - Pre-Alpha
Classifier: Environment :: Console
Classifier: License :: OSI Approved :: BSD License
Classifier: Programming Language :: Python
Classifier: Topic :: Communications :: Telephony
Classifier: Topic :: Communications :: Internet Phone
Classifier: Topic :: Communications :: Conferencing
